domo_python/__init__.py
domo_python-0.0.13.dist-info/DESCRIPTION.rst
domo_python-0.0.13.dist-info/METADATA
domo_python-0.0.13.dist-info/RECORD
domo_python-0.0.13.dist-info/WHEEL
domo_python-0.0.13.dist-info/metadata.json
domo_python-0.0.13.dist-info/top_level.txt
