Metadata-Version: 2.0
Name: domo-python
Version: 0.0.13
Summary: Domo API functions to import and export data into usable Pandas dataframes and manage your Domo instancea
Home-page: https://github.com/brockcooper/domo_python
Author: Big Squid, Inc.
Author-email: bcooper@bigsquid.com
License: UNKNOWN
Platform: UNKNOWN
